wix3msi/__init__.py
wix3msi/__main__.py
wix3msi/commandmanager.py
wix3msi/filesystem/__init__.py
wix3msi/filesystem/directorynode.py
wix3msi/filesystem/filenode.py
wix3msi/filesystem/node.py
wix3msi/filesystem/nodemanager.py
wix3msi/filesystem/nodemetaclass.py
wix3msi/filesystem/nodetype.py
wix3msi/windows/__init__.py
wix3msi/windows/windows.py
wix3msi/wix3/__init__.py
wix3msi/wix3/builder.py
wix3msi/wix3/languagecode.py
wix3msi/wix3/wxsdocument.py
wix3msi/wix3/wxsid.py
wix3msi/wix3/wxstemplates.py
wix3msi/wix3/data/__init__.py
wix3msi/wix3/data/booleanattribute.py
wix3msi/wix3/data/content.py
wix3msi/wix3/data/guidattribute.py
wix3msi/wix3/data/idattribute.py
wix3msi/wix3/schema/__init__.py
wix3msi/wix3/schema/component.py
wix3msi/wix3/schema/componentgroup.py
wix3msi/wix3/schema/componentgroupref.py
wix3msi/wix3/schema/componentref.py
wix3msi/wix3/schema/condition.py
wix3msi/wix3/schema/createfolder.py
wix3msi/wix3/schema/custom.py
wix3msi/wix3/schema/customaction.py
wix3msi/wix3/schema/directory.py
wix3msi/wix3/schema/directoryref.py
wix3msi/wix3/schema/directorysearch.py
wix3msi/wix3/schema/feature.py
wix3msi/wix3/schema/file.py
wix3msi/wix3/schema/filesearch.py
wix3msi/wix3/schema/fragment.py
wix3msi/wix3/schema/installexecutesequence.py
wix3msi/wix3/schema/mediatemplate.py
wix3msi/wix3/schema/package.py
wix3msi/wix3/schema/product.py
wix3msi/wix3/schema/property.py
wix3msi/wix3/schema/ui.py
wix3msi/wix3/schema/uiref.py
wix3msi/wix3/schema/wix.py
wix3msi/wix3/schema/wixvariable.py
wix3msi-0.0.66.dist-info/LICENSE
wix3msi-0.0.66.dist-info/METADATA
wix3msi-0.0.66.dist-info/WHEEL
wix3msi-0.0.66.dist-info/entry_points.txt
wix3msi-0.0.66.dist-info/top_level.txt
wix3msi-0.0.66.dist-info/RECORD
