Metadata-Version: 2.2
Name: wix3msi
Version: 0.0.66
Summary: Create robust and reliable Windows installers with ease. This library leverages Wix Toolset v3 to generate XML definitions, allowing developers to focus on installation logic instead of XML syntax.
Home-page: https://ddukbaek2.com
Author: ddukbaek2
Author-email: ddukbaek2@gmail.com
Classifier: Programming Language :: Python :: 3
Classifier: License :: OSI Approved :: MIT License
Classifier: Operating System :: Microsoft :: Windows
Requires-Python: >=3.9.7
License-File: LICENSE
Requires-Dist: xid-xpl
Dynamic: author
Dynamic: author-email
Dynamic: classifier
Dynamic: description
Dynamic: description-content-type
Dynamic: home-page
Dynamic: requires-dist
Dynamic: requires-python
Dynamic: summary
